{
  "users": [
    {
      "id": 1,
      "name": "renamed",
      "age": 2222020
    },
    {
      "age": 2929,
      "name": "new ",
      "id": 2
    },
    {
      "name": "new name",
      "age": 20220,
      "id": 3
    },
    {
      "name": "new naaaoiwoajme",
      "age": 3399,
      "id": 4
    },
    {
      "name": "new naaaoiwoajme",
      "age": 3399,
      "id": 5
    },
    {
      "name": "new naaaoiwoajme",
      "age": 3399,
      "id": 6
    },
    {
      "name": "new naaaoiwoajme",
      "age": 3399,
      "id": 7
    },
    {
      "name": "new naaaoiwoajme",
      "age": 3399,
      "id": 8
    }
  ]
}